triz_ai/__init__.py
triz_ai/ariz.py
triz_ai/assess_patentability.py
triz_ai/check_novelty.py
triz_ai/claim_validator.py
triz_ai/cli.py
triz_ai/drawing_mapper.py
triz_ai/generate_formula.py
triz_ai/ipc_classifier.py
triz_ai/prompt_enhancer.py
triz_ai/run_benchmark.py
triz_ai/run_tests.py
triz_ai/security_utils.py
triz_ai/streamlit_app.py
triz_ai/test_generate_formula.py
triz_ai/test_prompt_enhancer.py
triz_ai/triz_system.py
triz_ai/__pycache__/__init__.cpython-311.pyc
triz_ai/__pycache__/generate_formula.cpython-311.pyc
triz_ai_patent_assistant-0.1.26.dist-info/licenses/LICENSE
triz_ai_patent_assistant-0.1.26.dist-info/METADATA
triz_ai_patent_assistant-0.1.26.dist-info/WHEEL
triz_ai_patent_assistant-0.1.26.dist-info/top_level.txt
triz_ai_patent_assistant-0.1.26.dist-info/RECORD
