Metadata-Version: 2.4
Name: triz-ai-patent-assistant
Version: 0.1.26
Summary: AI‑assisted TRIZ patent analysis toolkit
Author-email: Sergei Voronin <voroninsergeiai@gmail.com>
License: MIT
Project-URL: Homepage, https://github.com/voroninsergei/triz-ai-patent-assistant
Project-URL: Documentation, https://voroninsergei.github.io/triz-ai-patent-assistant/
Project-URL: Source, https://github.com/voroninsergei/triz-ai-patent-assistant
Project-URL: Issues, https://github.com/voroninsergei/triz-ai-patent-assistant/issues
Project-URL: PyPI, https://pypi.org/project/triz-ai-patent-assistant/
Classifier: License :: OSI Approved :: MIT License
Classifier: Programming Language :: Python
Classifier: Programming Language :: Python :: 3
Classifier: Programming Language :: Python :: 3 :: Only
Classifier: Programming Language :: Python :: 3.8
Classifier: Development Status :: 3 - Alpha
Classifier: Intended Audience :: Developers
Classifier: Topic :: Scientific/Engineering
Requires-Python: >=3.8
License-File: LICENSE
Requires-Dist: openai>=1.0.0
Requires-Dist: mkdocs>=1.5.3
Requires-Dist: rich>=13.5.2
Dynamic: license-file
